odoo10_addon_auth_keycloak-10.0.1.1.0-nspkg.pth
odoo/addons/auth_keycloak/README.rst
odoo/addons/auth_keycloak/__init__.py
odoo/addons/auth_keycloak/__manifest__.py
odoo/addons/auth_keycloak/exceptions.py
odoo/addons/auth_keycloak/data/auth_oauth_provider.xml
odoo/addons/auth_keycloak/examples/README.md
odoo/addons/auth_keycloak/examples/__init__.py
odoo/addons/auth_keycloak/examples/cli.py
odoo/addons/auth_keycloak/examples/common.py
odoo/addons/auth_keycloak/examples/get_token.py
odoo/addons/auth_keycloak/examples/keycloak-compose.yml
odoo/addons/auth_keycloak/examples/odoo-client.json
odoo/addons/auth_keycloak/examples/realm-export.json
odoo/addons/auth_keycloak/examples/requirements.txt
odoo/addons/auth_keycloak/i18n/auth_keycloak.pot
odoo/addons/auth_keycloak/i18n/fr.po
odoo/addons/auth_keycloak/models/__init__.py
odoo/addons/auth_keycloak/models/auth_oauth.py
odoo/addons/auth_keycloak/models/res_users.py
odoo/addons/auth_keycloak/readme/CONFIGURE.rst
odoo/addons/auth_keycloak/readme/CONTRIBUTORS.rst
odoo/addons/auth_keycloak/readme/CREDITS.rst
odoo/addons/auth_keycloak/readme/DESCRIPTION.rst
odoo/addons/auth_keycloak/readme/HISTORY.rst
odoo/addons/auth_keycloak/readme/USAGE.rst
odoo/addons/auth_keycloak/static/description/icon.png
odoo/addons/auth_keycloak/static/description/index.html
odoo/addons/auth_keycloak/tests/__init__.py
odoo/addons/auth_keycloak/tests/common.py
odoo/addons/auth_keycloak/tests/test_auth.py
odoo/addons/auth_keycloak/tests/test_wizard_create.py
odoo/addons/auth_keycloak/tests/test_wizard_sync.py
odoo/addons/auth_keycloak/views/auth_oauth_views.xml
odoo/addons/auth_keycloak/views/res_users_views.xml
odoo/addons/auth_keycloak/wizard/__init__.py
odoo/addons/auth_keycloak/wizard/keycloak_create_wiz.xml
odoo/addons/auth_keycloak/wizard/keycloak_sync_wiz.py
odoo/addons/auth_keycloak/wizard/keycloak_sync_wiz.xml
odoo10_addon_auth_keycloak-10.0.1.1.0.dist-info/METADATA
odoo10_addon_auth_keycloak-10.0.1.1.0.dist-info/WHEEL
odoo10_addon_auth_keycloak-10.0.1.1.0.dist-info/namespace_packages.txt
odoo10_addon_auth_keycloak-10.0.1.1.0.dist-info/top_level.txt
odoo10_addon_auth_keycloak-10.0.1.1.0.dist-info/RECORD
